[{"extraction_method":"stream","top":0.0,"left":0.0,"width":595.0,"height":841.0,"right":595.0,"bottom":841.0,"data":[[{"top":0.0,"left":0.0,"width":0.0,"height":0.0,"text":""},{"top":21.45,"left":124.26,"width":184.10000610351562,"height":12.0,"text":"LÍNEA INDUSTRIAL"},{"top":0.0,"left":0.0,"width":0.0,"height":0.0,"text":""}],[{"top":0.0,"left":0.0,"width":0.0,"height":0.0,"text":""},{"top":143.79,"left":152.0,"width":291.0099792480469,"height":6.0,"text":"PERNO HEXAGONAL MÉTRICO RC - CL. 5.8 TROPICALIZADO"},{"top":0.0,"left":0.0,"width":0.0,"height":0.0,"text":""}],[{"top":0.0,"left":0.0,"width":0.0,"height":0.0,"text":""},{"top":161.45,"left":211.27,"width":231.55999755859375,"height":4.0,"text":"M2205 M2206 M2208 M2210 E2212"},{"top":0.0,"left":0.0,"width":0.0,"height":0.0,"text":""}],[{"top":0.0,"left":0.0,"width":0.0,"height":0.0,"text":""},{"top":175.7,"left":143.2,"width":300.75,"height":4.0,"text":"CÓD. LARGO Ø M5 Ø M6 Ø M8 Ø M10 Ø M12"},{"top":0.0,"left":0.0,"width":0.0,"height":0.0,"text":""}],[{"top":0.0,"left":0.0,"width":0.0,"height":0.0,"text":""},{"top":189.95,"left":213.67,"width":70.70999145507812,"height":4.0,"text":"$1.89 $2.27"},{"top":0.0,"left":0.0,"width":0.0,"height":0.0,"text":""}],[{"top":0.0,"left":0.0,"width":0.0,"height":0.0,"text":""},{"top":197.07,"left":147.26,"width":38.2500114440918,"height":4.0,"text":"02 10"},{"top":0.0,"left":0.0,"width":0.0,"height":0.0,"text":""}],[{"top":0.0,"left":0.0,"width":0.0,"height":0.0,"text":""},{"top":204.2,"left":209.17,"width":77.70001220703125,"height":4.0,"text":"100 CTO 60 CTO"},{"top":0.0,"left":0.0,"width":0.0,"height":0.0,"text":""}],[{"top":0.0,"left":0.0,"width":0.0,"height":0.0,"text":""},{"top":218.45,"left":213.67,"width":123.20999145507812,"height":4.0,"text":"$2.45 $2.68 $5.48"},{"top":0.0,"left":0.0,"width":0.0,"height":0.0,"text":""}],[{"top":0.0,"left":0.0,"width":0.0,"height":0.0,"text":""},{"top":225.57,"left":147.26,"width":38.2500114440918,"height":4.0,"text":"03 15"},{"top":0.0,"left":0.0,"width":0.0,"height":0.0,"text":""}],[{"top":0.0,"left":0.0,"width":0.0,"height":0.0,"text":""},{"top":232.7,"left":211.2,"width":128.17001342773438,"height":4.0,"text":"77 CTO 50 CTO 25 CTO"},{"top":0.0,"left":0.0,"width":0.0,"height":0.0,"text":""}],[{"top":0.0,"left":0.0,"width":0.0,"height":0.0,"text":""},{"top":246.95,"left":213.67,"width":123.20999145507812,"height":4.0,"text":"$2.66 $3.04 $5.99"},{"top":0.0,"left":0.0,"width":0.0,"height":0.0,"text":""}],[{"top":0.0,"left":0.0,"width":0.0,"height":0.0,"text":""},{"top":254.07,"left":147.26,"width":38.2500114440918,"height":4.0,"text":"04 20"},{"top":0.0,"left":0.0,"width":0.0,"height":0.0,"text":""}],[{"top":0.0,"left":0.0,"width":0.0,"height":0.0,"text":""},{"top":261.2,"left":211.2,"width":128.17001342773438,"height":4.0,"text":"68 CTO 43 CTO 21 CTO"},{"top":0.0,"left":0.0,"width":0.0,"height":0.0,"text":""}],[{"top":0.0,"left":0.0,"width":0.0,"height":0.0,"text":""},{"top":275.45,"left":213.67,"width":123.20999145507812,"height":4.0,"text":"$3.25 $3.52 $7.17"},{"top":0.0,"left":0.0,"width":0.0,"height":0.0,"text":""}],[{"top":0.0,"left":0.0,"width":0.0,"height":0.0,"text":""},{"top":282.57,"left":147.26,"width":38.2500114440918,"height":4.0,"text":"05 25"},{"top":0.0,"left":0.0,"width":0.0,"height":0.0,"text":""}],[{"top":0.0,"left":0.0,"width":0.0,"height":0.0,"text":""},{"top":289.7,"left":208.17,"width":134.23001098632812,"height":4.0,"text":"55.5 CTO 37.5 CTO 18.5 CTO"},{"top":0.0,"left":0.0,"width":0.0,"height":0.0,"text":""}],[{"top":0.0,"left":0.0,"width":0.0,"height":0.0,"text":""},{"top":303.95,"left":213.67,"width":230.239990234375,"height":4.0,"text":"$3.88 $3.94 $8.00 $12.72 $68.05"},{"top":0.0,"left":0.0,"width":0.0,"height":0.0,"text":""}],[{"top":0.0,"left":0.0,"width":0.0,"height":0.0,"text":""},{"top":311.07,"left":147.26,"width":38.2500114440918,"height":4.0,"text":"06 30"},{"top":0.0,"left":0.0,"width":0.0,"height":0.0,"text":""}],[{"top":0.0,"left":0.0,"width":0.0,"height":0.0,"text":""},{"top":318.2,"left":211.2,"width":234.17999267578125,"height":4.0,"text":"50 CTO 33.5 CTO 17 CTO 9.5 CTO 1.9 CTO"},{"top":0.0,"left":0.0,"width":0.0,"height":0.0,"text":""}],[{"top":0.0,"left":0.0,"width":0.0,"height":0.0,"text":""},{"top":332.45,"left":213.67,"width":177.739990234375,"height":4.0,"text":"$4.27 $4.35 $8.41 $14.40"},{"top":0.0,"left":0.0,"width":0.0,"height":0.0,"text":""}],[{"top":0.0,"left":0.0,"width":0.0,"height":0.0,"text":""},{"top":339.57,"left":147.26,"width":38.2500114440918,"height":4.0,"text":"07 35"},{"top":0.0,"left":0.0,"width":0.0,"height":0.0,"text":""}],[{"top":0.0,"left":0.0,"width":0.0,"height":0.0,"text":""},{"top":346.7,"left":211.2,"width":181.67999267578125,"height":4.0,"text":"43 CTO 29 CTO 15 CTO 8.8 CTO"},{"top":0.0,"left":0.0,"width":0.0,"height":0.0,"text":""}],[{"top":0.0,"left":0.0,"width":0.0,"height":0.0,"text":""},{"top":360.95,"left":213.67,"width":230.239990234375,"height":4.0,"text":"$4.83 $4.87 $9.19 $16.05 $77.36"},{"top":0.0,"left":0.0,"width":0.0,"height":0.0,"text":""}],[{"top":0.0,"left":0.0,"width":0.0,"height":0.0,"text":""},{"top":368.07,"left":147.26,"width":38.2500114440918,"height":4.0,"text":"08 40"},{"top":0.0,"left":0.0,"width":0.0,"height":0.0,"text":""}],[{"top":0.0,"left":0.0,"width":0.0,"height":0.0,"text":""},{"top":375.2,"left":211.2,"width":234.17999267578125,"height":4.0,"text":"39 CTO 27 CTO 13.5 CTO 8 CTO 1.7 CTO"},{"top":0.0,"left":0.0,"width":0.0,"height":0.0,"text":""}],[{"top":0.0,"left":0.0,"width":0.0,"height":0.0,"text":""},{"top":389.45,"left":213.67,"width":230.239990234375,"height":4.0,"text":"$5.62 $5.62 $10.79 $17.65 $89.60"},{"top":0.0,"left":0.0,"width":0.0,"height":0.0,"text":""}],[{"top":0.0,"left":0.0,"width":0.0,"height":0.0,"text":""},{"top":396.57,"left":147.26,"width":38.2500114440918,"height":4.0,"text":"10 50"},{"top":0.0,"left":0.0,"width":0.0,"height":0.0,"text":""}],[{"top":0.0,"left":0.0,"width":0.0,"height":0.0,"text":""},{"top":403.7,"left":211.2,"width":236.20001220703125,"height":4.0,"text":"30 CTO 20 CTO 11 CTO 6 CTO 1.42 CTO"},{"top":0.0,"left":0.0,"width":0.0,"height":0.0,"text":""}],[{"top":0.0,"left":0.0,"width":0.0,"height":0.0,"text":""},{"top":417.95,"left":266.17,"width":179.75999450683594,"height":4.0,"text":"$6.56 $12.24 $20.07 $103.82"},{"top":0.0,"left":0.0,"width":0.0,"height":0.0,"text":""}],[{"top":0.0,"left":0.0,"width":0.0,"height":0.0,"text":""},{"top":425.07,"left":147.26,"width":38.2500114440918,"height":4.0,"text":"12 60"},{"top":0.0,"left":0.0,"width":0.0,"height":0.0,"text":""}],[{"top":0.0,"left":0.0,"width":0.0,"height":0.0,"text":""},{"top":432.2,"left":263.7,"width":181.6799774169922,"height":4.0,"text":"16 CTO 10 CTO 6 CTO 1.2 CTO"},{"top":0.0,"left":0.0,"width":0.0,"height":0.0,"text":""}],[{"top":0.0,"left":0.0,"width":0.0,"height":0.0,"text":""},{"top":446.45,"left":316.65,"width":129.28001403808594,"height":4.0,"text":"$14.36 $118.60"},{"top":0.0,"left":0.0,"width":0.0,"height":0.0,"text":""}],[{"top":0.0,"left":0.0,"width":0.0,"height":0.0,"text":""},{"top":453.57,"left":147.26,"width":38.2500114440918,"height":4.0,"text":"14 70"},{"top":0.0,"left":0.0,"width":0.0,"height":0.0,"text":""}],[{"top":0.0,"left":0.0,"width":0.0,"height":0.0,"text":""},{"top":460.7,"left":318.22,"width":129.1800079345703,"height":4.0,"text":"7 CTO 1.05 CTO"},{"top":0.0,"left":0.0,"width":0.0,"height":0.0,"text":""}],[{"top":0.0,"left":0.0,"width":0.0,"height":0.0,"text":""},{"top":474.95,"left":316.65,"width":129.28001403808594,"height":4.0,"text":"$16.31 $133.80"},{"top":0.0,"left":0.0,"width":0.0,"height":0.0,"text":""}],[{"top":0.0,"left":0.0,"width":0.0,"height":0.0,"text":""},{"top":482.07,"left":147.26,"width":38.2500114440918,"height":4.0,"text":"16 80"},{"top":0.0,"left":0.0,"width":0.0,"height":0.0,"text":""}],[{"top":0.0,"left":0.0,"width":0.0,"height":0.0,"text":""},{"top":489.2,"left":318.22,"width":127.15998840332031,"height":4.0,"text":"7 CTO 0.9 CTO"},{"top":0.0,"left":0.0,"width":0.0,"height":0.0,"text":""}],[{"top":0.0,"left":0.0,"width":0.0,"height":0.0,"text":""},{"top":503.45,"left":316.65,"width":129.28001403808594,"height":4.0,"text":"$19.23 $156.23"},{"top":0.0,"left":0.0,"width":0.0,"height":0.0,"text":""}],[{"top":0.0,"left":0.0,"width":0.0,"height":0.0,"text":""},{"top":510.57,"left":147.26,"width":40.27000045776367,"height":4.0,"text":"20 100"},{"top":0.0,"left":0.0,"width":0.0,"height":0.0,"text":""}],[{"top":0.0,"left":0.0,"width":0.0,"height":0.0,"text":""},{"top":517.7,"left":315.19,"width":130.1899871826172,"height":4.0,"text":"6.5 CTO 0.8 CTO"},{"top":0.0,"left":0.0,"width":0.0,"height":0.0,"text":""}],[{"top":0.0,"left":0.0,"width":0.0,"height":0.0,"text":""},{"top":531.95,"left":224.14,"width":147.02999877929688,"height":4.0,"text":"PRECIO DE VENTA POR CIENTO (INCLUYE IGV)"},{"top":0.0,"left":0.0,"width":0.0,"height":0.0,"text":""}],[{"top":0.0,"left":0.0,"width":0.0,"height":0.0,"text":""},{"top":560.45,"left":199.26,"width":196.75999450683594,"height":4.0,"text":"TUERCA HEXAGONAL MÉTRICA RC - CL. 5.8 TROPICALIZADO"},{"top":0.0,"left":0.0,"width":0.0,"height":0.0,"text":""}],[{"top":0.0,"left":0.0,"width":0.0,"height":0.0,"text":""},{"top":574.7,"left":218.73,"width":218.10000610351562,"height":4.0,"text":"05 06 08 10 12"},{"top":0.0,"left":0.0,"width":0.0,"height":0.0,"text":""}],[{"top":0.0,"left":0.0,"width":0.0,"height":0.0,"text":""},{"top":588.95,"left":158.27,"width":285.67999267578125,"height":4.0,"text":"CÓD. Ø M5 Ø M6 Ø M8 Ø M10 Ø M12"},{"top":0.0,"left":0.0,"width":0.0,"height":0.0,"text":""}],[{"top":0.0,"left":0.0,"width":0.0,"height":0.0,"text":""},{"top":603.2,"left":213.67,"width":228.20999145507812,"height":4.0,"text":"$0.51 $1.10 $2.50 $5.35 $8.54"},{"top":0.0,"left":0.0,"width":0.0,"height":0.0,"text":""}],[{"top":0.0,"left":0.0,"width":0.0,"height":0.0,"text":""},{"top":610.32,"left":154.87,"width":23.030010223388672,"height":4.0,"text":"M0203"},{"top":0.0,"left":0.0,"width":0.0,"height":0.0,"text":""}],[{"top":0.0,"left":0.0,"width":0.0,"height":0.0,"text":""},{"top":617.45,"left":209.17,"width":235.20001220703125,"height":4.0,"text":"180 CTO 120 CTO 54 CTO 21 CTO 14 CTO"},{"top":0.0,"left":0.0,"width":0.0,"height":0.0,"text":""}],[{"top":0.0,"left":0.0,"width":0.0,"height":0.0,"text":""},{"top":631.7,"left":185.27,"width":224.75999450683594,"height":4.0,"text":"ARANDELA PLANA ESTÁNDAR MÉTRICO RC - CL. 5.8 TROPICALIZADO"},{"top":0.0,"left":0.0,"width":0.0,"height":0.0,"text":""}],[{"top":0.0,"left":0.0,"width":0.0,"height":0.0,"text":""},{"top":645.95,"left":218.73,"width":218.10000610351562,"height":4.0,"text":"05 06 08 10 12"},{"top":0.0,"left":0.0,"width":0.0,"height":0.0,"text":""}],[{"top":0.0,"left":0.0,"width":0.0,"height":0.0,"text":""},{"top":660.2,"left":158.27,"width":285.67999267578125,"height":4.0,"text":"CÓD. Ø M5 Ø M6 Ø M8 Ø M10 Ø M12"},{"top":0.0,"left":0.0,"width":0.0,"height":0.0,"text":""}],[{"top":0.0,"left":0.0,"width":0.0,"height":0.0,"text":""},{"top":674.45,"left":266.17,"width":175.70997619628906,"height":4.0,"text":"$0.55 $0.96 $1.70 $3.14"},{"top":0.0,"left":0.0,"width":0.0,"height":0.0,"text":""}],[{"top":0.0,"left":0.0,"width":0.0,"height":0.0,"text":""},{"top":681.57,"left":154.87,"width":23.030010223388672,"height":4.0,"text":"M1209"},{"top":0.0,"left":0.0,"width":0.0,"height":0.0,"text":""}],[{"top":0.0,"left":0.0,"width":0.0,"height":0.0,"text":""},{"top":688.7,"left":268.65,"width":170.77000427246094,"height":4.0,"text":"CTO CTO CTO CTO"},{"top":0.0,"left":0.0,"width":0.0,"height":0.0,"text":""}],[{"top":0.0,"left":0.0,"width":0.0,"height":0.0,"text":""},{"top":702.95,"left":224.14,"width":147.02999877929688,"height":4.0,"text":"PRECIO DE VENTA POR CIENTO (INCLUYE IGV)"},{"top":0.0,"left":0.0,"width":0.0,"height":0.0,"text":""}],[{"top":813.5,"left":49.01,"width":31.416004180908203,"height":6.0,"text":"Índice"},{"top":813.5,"left":250.07,"width":92.56597900390625,"height":6.0,"text":"www.dina.com.pe"},{"top":813.5,"left":574.86,"width":12.140007019042969,"height":6.0,"text":"57"}]]}]