[{"extraction_method":"stream","top":0.0,"left":0.0,"width":595.0,"height":841.0,"right":595.0,"bottom":841.0,"data":[[{"top":0.0,"left":0.0,"width":0.0,"height":0.0,"text":""},{"top":0.0,"left":0.0,"width":0.0,"height":0.0,"text":""},{"top":0.0,"left":0.0,"width":0.0,"height":0.0,"text":""},{"top":0.0,"left":0.0,"width":0.0,"height":0.0,"text":""},{"top":0.0,"left":0.0,"width":0.0,"height":0.0,"text":""},{"top":0.0,"left":0.0,"width":0.0,"height":0.0,"text":""},{"top":21.45,"left":245.02,"width":267.45001220703125,"height":12.0,"text":"COMPLEMENTOS DE LÍNEA"}],[{"top":0.0,"left":0.0,"width":0.0,"height":0.0,"text":""},{"top":0.0,"left":0.0,"width":0.0,"height":0.0,"text":""},{"top":0.0,"left":0.0,"width":0.0,"height":0.0,"text":""},{"top":0.0,"left":0.0,"width":0.0,"height":0.0,"text":""},{"top":0.0,"left":0.0,"width":0.0,"height":0.0,"text":""},{"top":0.0,"left":0.0,"width":0.0,"height":0.0,"text":""},{"top":210.96,"left":459.65,"width":54.08002471923828,"height":3.5,"text":"Imagen referencial"}],[{"top":0.0,"left":0.0,"width":0.0,"height":0.0,"text":""},{"top":0.0,"left":0.0,"width":0.0,"height":0.0,"text":""},{"top":0.0,"left":0.0,"width":0.0,"height":0.0,"text":""},{"top":0.0,"left":0.0,"width":0.0,"height":0.0,"text":""},{"top":0.0,"left":0.0,"width":0.0,"height":0.0,"text":""},{"top":0.0,"left":0.0,"width":0.0,"height":0.0,"text":""},{"top":222.46,"left":234.64,"width":126.02001190185547,"height":4.0,"text":"PASADOR DE FIERRO PARA HORQUILLA"}],[{"top":0.0,"left":0.0,"width":0.0,"height":0.0,"text":""},{"top":0.0,"left":0.0,"width":0.0,"height":0.0,"text":""},{"top":238.21,"left":126.61,"width":6.204010009765625,"height":4.0,"text":"Ø"},{"top":0.0,"left":0.0,"width":0.0,"height":0.0,"text":""},{"top":238.21,"left":178.69,"width":15.29400634765625,"height":4.0,"text":"1/8\""},{"top":0.0,"left":0.0,"width":0.0,"height":0.0,"text":""},{"top":238.21,"left":251.67,"width":243.42999267578125,"height":4.0,"text":"5/32\" 3/16\" 1/4\" 5/16\""}],[{"top":0.0,"left":0.0,"width":0.0,"height":0.0,"text":""},{"top":250.96,"left":79.72,"width":23.494003295898438,"height":4.0,"text":"LARGO"},{"top":0.0,"left":0.0,"width":0.0,"height":0.0,"text":""},{"top":0.0,"left":0.0,"width":0.0,"height":0.0,"text":""},{"top":253.21,"left":196.71,"width":17.670000076293945,"height":4.0,"text":"EMP."},{"top":0.0,"left":0.0,"width":0.0,"height":0.0,"text":""},{"top":253.21,"left":271.71,"width":242.67001342773438,"height":4.0,"text":"EMP. EMP. EMP. EMP."}],[{"top":0.0,"left":0.0,"width":0.0,"height":0.0,"text":""},{"top":0.0,"left":0.0,"width":0.0,"height":0.0,"text":""},{"top":258.84,"left":121.15,"width":17.154014587402344,"height":4.0,"text":"CÓD."},{"top":258.84,"left":157.09,"width":20.9940185546875,"height":4.0,"text":"E7001"},{"top":0.0,"left":0.0,"width":0.0,"height":0.0,"text":""},{"top":0.0,"left":0.0,"width":0.0,"height":0.0,"text":""},{"top":258.84,"left":232.09,"width":245.0900115966797,"height":4.0,"text":"E7001 E7003 E7004 E7005"}],[{"top":0.0,"left":0.0,"width":0.0,"height":0.0,"text":""},{"top":0.0,"left":0.0,"width":0.0,"height":0.0,"text":""},{"top":0.0,"left":0.0,"width":0.0,"height":0.0,"text":""},{"top":0.0,"left":0.0,"width":0.0,"height":0.0,"text":""},{"top":264.46,"left":195.44,"width":19.143218994140625,"height":4.0,"text":"(uds.)"},{"top":0.0,"left":0.0,"width":0.0,"height":0.0,"text":""},{"top":264.46,"left":270.44,"width":243.38999938964844,"height":4.0,"text":"(uds.) (uds.) (uds.) (uds.)"}],[{"top":0.0,"left":0.0,"width":0.0,"height":0.0,"text":""},{"top":279.46,"left":87.39,"width":8.143997192382812,"height":4.0,"text":"1\""},{"top":279.46,"left":125.21,"width":9.004005432128906,"height":4.0,"text":"04"},{"top":279.46,"left":158.03,"width":19.114013671875,"height":4.0,"text":"$1.75"},{"top":279.46,"left":193.51,"width":23.144012451171875,"height":4.0,"text":"10,000"},{"top":0.0,"left":0.0,"width":0.0,"height":0.0,"text":""},{"top":279.46,"left":233.03,"width":130.6999969482422,"height":4.75,"text":"$1.75 10,000 $4.55 5,000"}],[{"top":0.0,"left":0.0,"width":0.0,"height":0.0,"text":""},{"top":295.21,"left":80.89,"width":21.143997192382812,"height":4.0,"text":"1 1/2\""},{"top":295.21,"left":125.21,"width":9.004005432128906,"height":4.0,"text":"06"},{"top":295.21,"left":158.03,"width":19.114013671875,"height":4.0,"text":"$2.20"},{"top":295.21,"left":193.51,"width":23.144012451171875,"height":4.0,"text":"10,000"},{"top":0.0,"left":0.0,"width":0.0,"height":0.0,"text":""},{"top":295.21,"left":233.03,"width":205.6999969482422,"height":4.75,"text":"$2.20 10,000 $4.96 4,000 $8.74 2,200"}],[{"top":0.0,"left":0.0,"width":0.0,"height":0.0,"text":""},{"top":310.96,"left":87.39,"width":8.143997192382812,"height":4.0,"text":"2\""},{"top":310.96,"left":125.21,"width":9.004005432128906,"height":4.0,"text":"08"},{"top":310.96,"left":158.03,"width":19.114013671875,"height":4.0,"text":"$2.81"},{"top":310.96,"left":193.51,"width":23.144012451171875,"height":4.0,"text":"10,000"},{"top":0.0,"left":0.0,"width":0.0,"height":0.0,"text":""},{"top":310.96,"left":233.03,"width":205.6999969482422,"height":4.75,"text":"$2.81 10,000 $6.83 3,500 $9.12 1,800"}],[{"top":0.0,"left":0.0,"width":0.0,"height":0.0,"text":""},{"top":326.71,"left":80.89,"width":21.143997192382812,"height":4.0,"text":"2 1/2\""},{"top":326.71,"left":125.21,"width":9.004005432128906,"height":4.0,"text":"10"},{"top":0.0,"left":0.0,"width":0.0,"height":0.0,"text":""},{"top":0.0,"left":0.0,"width":0.0,"height":0.0,"text":""},{"top":0.0,"left":0.0,"width":0.0,"height":0.0,"text":""},{"top":327.46,"left":308.03,"width":130.6999969482422,"height":4.0,"text":"$6.51 2,200 $13.64 1,550"}],[{"top":0.0,"left":0.0,"width":0.0,"height":0.0,"text":""},{"top":342.46,"left":87.39,"width":8.143997192382812,"height":4.0,"text":"3\""},{"top":342.46,"left":125.21,"width":9.004005432128906,"height":4.0,"text":"12"},{"top":0.0,"left":0.0,"width":0.0,"height":0.0,"text":""},{"top":0.0,"left":0.0,"width":0.0,"height":0.0,"text":""},{"top":0.0,"left":0.0,"width":0.0,"height":0.0,"text":""},{"top":343.21,"left":381.0,"width":57.7299919128418,"height":4.0,"text":"$14.00 1,200"}],[{"top":0.0,"left":0.0,"width":0.0,"height":0.0,"text":""},{"top":358.21,"left":80.89,"width":21.143997192382812,"height":4.0,"text":"3 1/2\""},{"top":358.21,"left":125.21,"width":9.004005432128906,"height":4.0,"text":"14"},{"top":0.0,"left":0.0,"width":0.0,"height":0.0,"text":""},{"top":0.0,"left":0.0,"width":0.0,"height":0.0,"text":""},{"top":0.0,"left":0.0,"width":0.0,"height":0.0,"text":""},{"top":358.96,"left":456.0,"width":54.71000289916992,"height":4.0,"text":"$28.85 950"}],[{"top":0.0,"left":0.0,"width":0.0,"height":0.0,"text":""},{"top":373.96,"left":87.39,"width":8.143997192382812,"height":4.0,"text":"4\""},{"top":373.96,"left":125.21,"width":9.004005432128906,"height":4.0,"text":"16"},{"top":0.0,"left":0.0,"width":0.0,"height":0.0,"text":""},{"top":0.0,"left":0.0,"width":0.0,"height":0.0,"text":""},{"top":0.0,"left":0.0,"width":0.0,"height":0.0,"text":""},{"top":374.71,"left":456.0,"width":54.71000289916992,"height":4.0,"text":"$31.46 755"}],[{"top":0.0,"left":0.0,"width":0.0,"height":0.0,"text":""},{"top":0.0,"left":0.0,"width":0.0,"height":0.0,"text":""},{"top":0.0,"left":0.0,"width":0.0,"height":0.0,"text":""},{"top":0.0,"left":0.0,"width":0.0,"height":0.0,"text":""},{"top":0.0,"left":0.0,"width":0.0,"height":0.0,"text":""},{"top":0.0,"left":0.0,"width":0.0,"height":0.0,"text":""},{"top":389.71,"left":231.19,"width":132.9199981689453,"height":4.0,"text":"PRECIO DE VENTA POR CIENTO (INC. IGV)"}],[{"top":813.5,"left":8.25,"width":19.56599998474121,"height":6.0,"text":"146"},{"top":0.0,"left":0.0,"width":0.0,"height":0.0,"text":""},{"top":0.0,"left":0.0,"width":0.0,"height":0.0,"text":""},{"top":0.0,"left":0.0,"width":0.0,"height":0.0,"text":""},{"top":0.0,"left":0.0,"width":0.0,"height":0.0,"text":""},{"top":0.0,"left":0.0,"width":0.0,"height":0.0,"text":""},{"top":813.5,"left":283.27,"width":261.0,"height":6.0,"text":"@dinafastener Índice"}]]}]